agentlabs/__init__.py
agentlabs/agent.py
agentlabs/registry.py
agentlabs/service_registry.py
agentlabs/models/enums.py
agentlabs/models/input_type.py
agentlabs/models/service.py
agentlabs/utils/logger.py
agentlabs/utils/utils.py
agentlabs-0.1.0.dist-info/LICENSE
agentlabs-0.1.0.dist-info/METADATA
agentlabs-0.1.0.dist-info/WHEEL
agentlabs-0.1.0.dist-info/top_level.txt
agentlabs-0.1.0.dist-info/RECORD
