Metadata-Version: 2.1
Name: agentlabs
Version: 0.1.0
Summary: agentlabs: A Python library for implementing agents on Weavel
Keywords: weavel,agent,llm,tools,agentlabs,llm agent
Requires-Python: >=3.7.1
License-File: LICENSE
Requires-Dist: pydantic
